__init__.py
vunit_helpers.py
VUnit_helpers-2023.5.7.dist-info/LICENSE
VUnit_helpers-2023.5.7.dist-info/METADATA
VUnit_helpers-2023.5.7.dist-info/WHEEL
VUnit_helpers-2023.5.7.dist-info/top_level.txt
VUnit_helpers-2023.5.7.dist-info/RECORD
