Metadata-Version: 2.1
Name: VUnit-helpers
Version: 2023.5.7
Summary: Common tools and helpers to simplify the VUnit run scripts
Author-email: Markus Leiter <leiter@p2l2.com>
Project-URL: Homepage, https://github.com/p2l2/VUnit-helpers
Project-URL: Bug Tracker, https://github.com/p2l2/VUnit-helpers/issues
Keywords: VUnit,unit testing
Classifier: License :: OSI Approved :: Mozilla Public License 2.0 (MPL 2.0)
Classifier: Natural Language :: English
Classifier: Intended Audience :: Developers
Classifier: Programming Language :: Python :: 3.7
Classifier: Programming Language :: Python :: 3.8
Classifier: Programming Language :: Python :: 3.9
Classifier: Programming Language :: Python :: 3.10
Classifier: Programming Language :: Python :: 3.11
Classifier: Operating System :: Microsoft :: Windows
Classifier: Operating System :: MacOS :: MacOS X
Classifier: Operating System :: POSIX :: Linux
Classifier: Topic :: Software Development :: Testing
Classifier: Topic :: Scientific/Engineering :: Electronic Design Automation (EDA)
Requires-Python: >=3.7
License-File: LICENSE
Requires-Dist: pathlib
Requires-Dist: logging
Requires-Dist: glob2
Requires-Dist: typing
Requires-Dist: toml (>=0.10.2)
